[
    {
        "key": "comp_status", 
        "name": "Component status", 
        "value": {
            "default": "Enabled", 
            "units": "-", 
            "type": "choice", 
            "choices": [
                "Enabled", 
                "Disabled"
            ]
        }, 
        "description": "component status"
    }, 
    {
        "key": "in_directory", 
        "name": "Input directory", 
        "value": {
            "default": "/home/csdms/models/topoflow/3.1/share/data/treynor_iowa/", 
            "units": "-", 
            "type": "string"
        }, 
        "description": "input directory"
    }, 
    {
        "key": "out_directory", 
        "name": "Output directory", 
        "value": {
            "default": "~/CMT_Output/", 
            "units": "-", 
            "type": "string"
        }, 
        "description": "output directory"
    }, 
    {
        "key": "site_prefix", 
        "name": "Site prefix", 
        "value": {
            "default": "Treynor", 
            "units": "-", 
            "type": "string"
        }, 
        "description": "file prefix for the study site"
    }, 
    {
        "key": "case_prefix", 
        "name": "Case prefix", 
        "value": {
            "default": "Case5", 
            "units": "-", 
            "type": "string"
        }, 
        "description": "file prefix for the model scenario"
    }, 
    {
        "key": "n_steps", 
        "name": "Number of steps", 
        "value": {
            "default": "10", 
            "units": "-", 
            "range": {
                "max": "1e7", 
                "min": "1"
            }, 
            "type": "long"
        }, 
        "description": "number of time steps"
    }, 
    {
        "key": "dt", 
        "name": "Time step", 
        "value": {
            "default": "10800.000", 
            "units": "sec", 
            "range": {
                "max": "1e4", 
                "min": "0.0"
            }, 
            "type": "float"
        }, 
        "description": "timestep for evaporation rate"
    }, 
    {
        "key": "ET_rate", 
        "name": "ET rate", 
        "value": {
            "default": "[case_prefix]_2D-ETrate-in.nc", 
            "units": "mm/hr", 
            "type": "string"
        }, 
        "description": "Grid Sequence"
    }, 
    {
        "key": "save_grid_dt", 
        "name": "Save grid timestep", 
        "value": {
            "default": "60.000", 
            "units": "sec", 
            "range": {
                "max": "1e6", 
                "min": "0.0"
            }, 
            "type": "float"
        }, 
        "description": "time interval between saved grids"
    }, 
    {
        "key": "SAVE_ER_GRIDS", 
        "name": "Save er grids toggle", 
        "value": {
            "default": "No", 
            "units": "mm/hr", 
            "type": "choice", 
            "choices": [
                "Yes", 
                "No"
            ]
        }, 
        "description": "option to save grids of evap. rate"
    }, 
    {
        "key": "er_gs_file", 
        "name": "Save er grids file", 
        "value": {
            "default": "[case_prefix]_2D-ETrate.nc", 
            "units": "mm/hr", 
            "type": "string"
        }, 
        "description": "filename for grid stack of evap. rate"
    }, 
    {
        "key": "save_pixels_dt", 
        "name": "Save pixels timestep", 
        "value": {
            "default": "60.000", 
            "units": "sec", 
            "range": {
                "max": "1e6", 
                "min": "0.0"
            }, 
            "type": "float"
        }, 
        "description": "time interval between time series values"
    }, 
    {
        "key": "pixel_file", 
        "name": "Monitored pixel file", 
        "value": {
            "default": "[case_prefix]_outlets.txt", 
            "units": "-", 
            "type": "string"
        }, 
        "description": "filename for monitored pixel file"
    }, 
    {
        "key": "SAVE_ER_PIXELS", 
        "name": "Save er pixels toggle", 
        "value": {
            "default": "No", 
            "units": "-", 
            "type": "choice", 
            "choices": [
                "Yes", 
                "No"
            ]
        }, 
        "description": "option to save time series of evap. rate"
    }, 
    {
        "key": "er_ts_file", 
        "name": "Save er pixels file", 
        "value": {
            "default": "[case_prefix]_0D-ETrate.txt", 
            "units": "mm/hr", 
            "type": "string"
        }, 
        "description": "filename for time series of evap. rate"
    }, 
    {
        "key": "ModelName", 
        "name": "Model name", 
        "value": {
            "default": "EvapReadFile", 
            "units": "-", 
            "type": "String"
        }, 
        "description": "Name of the model"
    }, 
    {
        "key": "ModelAuthor", 
        "name": "Author name", 
        "value": {
            "default": "Scott D. Peckham ", 
            "units": "-", 
            "type": "String"
        }, 
        "description": "Name of the model author"
    }, 
    {
        "key": "HTML_HELP_FILE", 
        "name": "HTML help file", 
        "value": {
            "default": "http://csdms.colorado.edu/wiki/Model_help:TopoFlow-Evaporation-Read_File", 
            "units": "-", 
            "type": "String"
        }, 
        "description": "URL for HTML help file"
    }
]